joker/__init__.py
joker/joker.py
joker/jokes/__init__.py
joker.py-0.0.1.dist-info/LICENSE
joker.py-0.0.1.dist-info/METADATA
joker.py-0.0.1.dist-info/WHEEL
joker.py-0.0.1.dist-info/top_level.txt
joker.py-0.0.1.dist-info/RECORD
