Metadata-Version: 2.1
Name: joker.py
Version: 0.0.1
Summary: Python package to get jokes and puns.
Home-page: https://github.com/diwash007/Joker.py
Author: diwash007
Author-email: diwashdahal75@gmail.com
License: UNKNOWN
Project-URL: Bug Tracker, https://github.com/diwash007/Joker.py/issues
Platform: UNKNOWN
Classifier: Programming Language :: Python :: 3
Classifier: License :: OSI Approved :: MIT License
Classifier: Operating System :: OS Independent
Requires-Python: >=3.6
License-File: LICENSE
